plc_main.py
plc_main-1.0.0.dist-info/WHEEL
plc_main-1.0.0.dist-info/METADATA
plc_main-1.0.0.dist-info/RECORD
