Metadata-Version: 2.1
Name: plc-main
Version: 1.0.0
Summary: Logical components in python.
License: none
Author: Your Name
Author-email: you@example.com
Requires-Python: >=3.9,<4.0
Classifier: License :: Other/Proprietary License
Classifier: Programming Language :: Python :: 3
Classifier: Programming Language :: Python :: 3.9
